[
  {
    "name": "Rina Marlina",
    "review": "Makanan tradisionalnya enak banget! Serasa makan masakan ibu di rumah.",
    "avatar": "https://avatar.iran.liara.run/public/69"
  },
  {
    "name": "Dewi Santika",
    "review": "Pelayanannya cepat dan ramah. Pasti order lagi!",
    "avatar": "https://avatar.iran.liara.run/public/65"
  },
  {
    "name": "Budi Hartono",
    "review": "Saya suka nasi bakarnya, bumbunya terasa autentik sekali.",
    "avatar": "https://avatar.iran.liara.run/public/7"
  },
  {
    "name": "Andi Prasetyo",
    "review": "Harga terjangkau dan rasanya luar biasa. Recommended!",
    "avatar": "https://avatar.iran.liara.run/public/43"
  },
  {
    "name": "Sari Wulandari",
    "review": "Camilannya enak-enak, cocok buat oleh-oleh keluarga.",
    "avatar": "https://avatar.iran.liara.run/public/85"
  }
]
